CHANGES.txt
MANIFEST.in
README.md
setup.py
clair/__init__.py
clair/clair.py
clair.egg-info/PKG-INFO
clair.egg-info/SOURCES.txt
clair.egg-info/dependency_links.txt
clair.egg-info/not-zip-safe
clair.egg-info/requires.txt
clair.egg-info/top_level.txt