Metadata-Version: 1.1
Name: clair
Version: 0.3
Summary: Import a Docker image layers to Clair for security analysis
Home-page: https://bitbucket.org/osallou/clair
Author: Olivier Sallou
Author-email: olivier.sallou@irisa.fr
License: UNKNOWN
Keywords: docker clair
Platform: UNKNOWN
Classifier: Programming Language :: Python
